sparsefile/__init__.py
sparsefile/exc.py
sparsefile/sparsifier.py
sparsefile/windows.py
sparsefile-0.1.0.dist-info/METADATA
sparsefile-0.1.0.dist-info/WHEEL
sparsefile-0.1.0.dist-info/top_level.txt
sparsefile-0.1.0.dist-info/RECORD
