Metadata-Version: 2.1
Name: sparsefile
Version: 0.1.0
Summary: Create sparse files and punch holes through existing files
Home-page: UNKNOWN
Author: Eduard Christian Dumitrescu
Author-email: eduard.c.dumitrescu@gmail.com
License: MIT
Platform: UNKNOWN
Classifier: Programming Language :: Python :: 3
Classifier: License :: OSI Approved :: MIT License
Classifier: Operating System :: MacOS :: MacOS X
Classifier: Operating System :: Microsoft :: Windows
Classifier: Operating System :: OS Independent
Classifier: Operating System :: POSIX :: Linux
